gbulb/__init__.py
gbulb/glib_events.py
gbulb/gtk.py
gbulb/transports.py
gbulb/utils.py
gbulb-0.6.6.dist-info/AUTHORS.rst
gbulb-0.6.6.dist-info/LICENSE
gbulb-0.6.6.dist-info/METADATA
gbulb-0.6.6.dist-info/WHEEL
gbulb-0.6.6.dist-info/top_level.txt
gbulb-0.6.6.dist-info/RECORD
